pyqplib/__init__.py
pyqplib/cons.py
pyqplib/desc.py
pyqplib/init_vals.py
pyqplib/log.py
pyqplib/lower_mat.py
pyqplib/obj.py
pyqplib/prob.py
pyqplib/reader.py
pyqplib/types.py
pyqplib/util.py
pyqplib-0.1.6.dist-info/METADATA
pyqplib-0.1.6.dist-info/WHEEL
pyqplib-0.1.6.dist-info/licenses/LICENSE
pyqplib-0.1.6.dist-info/RECORD
